kiriko/__init__.py
kiriko/shell/__init__.py
kiriko/shell/usage.py
kiriko/src/temp.txt
package_name/__init__.py
package_name/shell/__init__.py
package_name/shell/usage.py
package_name/src/temp.txt
kiriko-0.0.1.dist-info/LICENSE
kiriko-0.0.1.dist-info/METADATA
kiriko-0.0.1.dist-info/WHEEL
kiriko-0.0.1.dist-info/entry_points.txt
kiriko-0.0.1.dist-info/top_level.txt
kiriko-0.0.1.dist-info/zip-safe
kiriko-0.0.1.dist-info/RECORD
